README
setup.py
PushbulletPythonLibrary.egg-info/PKG-INFO
PushbulletPythonLibrary.egg-info/SOURCES.txt
PushbulletPythonLibrary.egg-info/dependency_links.txt
PushbulletPythonLibrary.egg-info/entry_points.txt
PushbulletPythonLibrary.egg-info/pbr.json
PushbulletPythonLibrary.egg-info/requires.txt
PushbulletPythonLibrary.egg-info/top_level.txt
pushbullet/__init__.py
pushbullet/cli.py
pushbullet/pushbullet.py