Metadata-Version: 1.1
Name: PushbulletPythonLibrary
Version: 2.3
Summary: A Python Library and a simple command line app for Pushbullet.
Home-page: https://github.com/myles/pushbullet
Author: Myles Braithwaite
Author-email: me@mylesbraithwaite.com
License: BSD
Keywords: pushbullet
Platform: UNKNOWN
Classifier: Development Status :: 3 - Alpha
Classifier: Topic :: Utilities
Classifier: License :: OSI Approved :: BSD License
